meteo_qc/__init__.py
meteo_qc/_colum_mapping.py
meteo_qc/_data.py
meteo_qc/_main.py
meteo_qc/_plugins/__init__.py
meteo_qc/_plugins/generic.py
meteo_qc/_plugins/values.py
meteo_qc-0.4.4.dist-info/licenses/LICENCE
meteo_qc-0.4.4.dist-info/METADATA
meteo_qc-0.4.4.dist-info/WHEEL
meteo_qc-0.4.4.dist-info/top_level.txt
meteo_qc-0.4.4.dist-info/RECORD
