Metadata-Version: 2.4
Name: meteo_qc
Version: 0.4.4
Summary: quality control meteorological data in a pandas.DataFrame
Home-page: https://github.com/jkittner/meteo-qc
Author: Jonas Kittner
Author-email: jkittner@users.noreply.github.com
License: MIT
Classifier: Programming Language :: Python :: 3
Classifier: Programming Language :: Python :: 3 :: Only
Classifier: Programming Language :: Python :: Implementation :: CPython
Requires-Python: >=3.10
License-File: LICENCE
Requires-Dist: pandas
Dynamic: license-file
